prefect_vault/__init__.py
prefect_vault/_version.py
prefect_vault/auth.py
prefect_vault/secret.py
prefect_vault-0.2.0.dist-info/LICENSE
prefect_vault-0.2.0.dist-info/METADATA
prefect_vault-0.2.0.dist-info/WHEEL
prefect_vault-0.2.0.dist-info/top_level.txt
prefect_vault-0.2.0.dist-info/RECORD
